[{
 "name": "Ivoclar Vivadent (Liechtenstein)",
 "country": "Liechtenstein",
 "types": [
  "Company"
 ]
},{
 "name": "Hilti (Liechtenstein)",
 "country": "Liechtenstein",
 "types": [
  "Company"
 ]
},{
 "name": "Oerlikon (Liechtenstein)",
 "country": "Liechtenstein",
 "types": [
  "Company"
 ]
},{
 "name": "International Academy of Philosophy",
 "country": "Liechtenstein",
 "types": [
  "Education"
 ]
},{
 "name": "Private University in the Principality of Liechtenstein",
 "country": "Liechtenstein",
 "types": [
  "Education"
 ]
},{
 "name": "University of Liechtenstein",
 "country": "Liechtenstein",
 "types": [
  "Education"
 ]
},{
 "name": "Ministry for Foreign Affairs, Education and Culture",
 "country": "Liechtenstein",
 "types": [
  "Government"
 ]
},{
 "name": "ThyssenKrupp (Liechtenstein)",
 "country": "Liechtenstein",
 "types": [
  "Company"
 ]
},{
 "name": "Lotex Foundation",
 "country": "Liechtenstein",
 "types": [
  "Other"
 ]
},{
 "name": "Liechtenstein Institute",
 "country": "Liechtenstein",
 "types": [
  "Facility"
 ]
},{
 "name": "Medicor Foundation",
 "country": "Liechtenstein",
 "types": [
  "Nonprofit"
 ]
},{
 "name": "Bemer (Liechtenstein)",
 "country": "Liechtenstein",
 "types": [
  "Company"
 ]
},{
 "name": "Commission Internationale pour la Protection des Alpes",
 "country": "Liechtenstein",
 "types": [
  "Other"
 ]
},{
 "name": "Bonyf (Liechtenstein)",
 "country": "Liechtenstein",
 "types": [
  "Company"
 ]
},{
 "name": "Lysando (Liechtenstein)",
 "country": "Liechtenstein",
 "types": [
  "Company"
 ]
}]