[{
 "name": "Institut Pasteur de Madagascar",
 "country_code": "MG",
 "country_name": "Madagascar",
 "types": [
  "Nonprofit"
 ]
},{
 "name": "Akbaraly Foundation",
 "country_code": "MG",
 "country_name": "Madagascar",
 "types": [
  "Nonprofit"
 ]
},{
 "name": "Centre National de la Recherche Appliqu\u00e9e au Developpement Rural",
 "country_code": "MG",
 "country_name": "Madagascar",
 "types": [
  "Facility"
 ]
},{
 "name": "University of Toliara",
 "country_code": "MG",
 "country_name": "Madagascar",
 "types": [
  "Education"
 ]
},{
 "name": "University of Antananarivo",
 "country_code": "MG",
 "country_name": "Madagascar",
 "types": [
  "Education"
 ]
},{
 "name": "\u00c9cole Nationale d'Administration de Madagascar",
 "country_code": "MG",
 "country_name": "Madagascar",
 "types": [
  "Education"
 ]
},{
 "name": "Hautes Etudes Chr\u00e9tiennes de Management et de Math\u00e9matiques Appliqu\u00e9es",
 "country_code": "MG",
 "country_name": "Madagascar",
 "types": [
  "Education"
 ]
},{
 "name": "Institut National des Sciences Comptables et de l\u2019Administration d\u2019Entreprises",
 "country_code": "MG",
 "country_name": "Madagascar",
 "types": [
  "Education"
 ]
},{
 "name": "Catholic University of Madagascar",
 "country_code": "MG",
 "country_name": "Madagascar",
 "types": [
  "Education"
 ]
},{
 "name": "Institut Sup\u00e9rieur de la Communication, des Affaires et du Management",
 "country_code": "MG",
 "country_name": "Madagascar",
 "types": [
  "Education"
 ]
},{
 "name": "Universit\u00e9 d\u2019Antsiranana",
 "country_code": "MG",
 "country_name": "Madagascar",
 "types": [
  "Education"
 ]
},{
 "name": "Universit\u00e9 de Mahajanga",
 "country_code": "MG",
 "country_name": "Madagascar",
 "types": [
  "Education"
 ]
},{
 "name": "University of Toamasina",
 "country_code": "MG",
 "country_name": "Madagascar",
 "types": [
  "Education"
 ]
},{
 "name": "Association Vahatra",
 "country_code": "MG",
 "country_name": "Madagascar",
 "types": [
  "Other"
 ]
},{
 "name": "Tsimbazaza Zoo",
 "country_code": "MG",
 "country_name": "Madagascar",
 "types": [
  "Archive"
 ]
},{
 "name": "Association Mitsinjo",
 "country_code": "MG",
 "country_name": "Madagascar",
 "types": [
  "Other"
 ]
},{
 "name": "Ministry of National Education and Scientific Research",
 "country_code": "MG",
 "country_name": "Madagascar",
 "types": [
  "Government"
 ]
},{
 "name": "Madagascar Biodiversity Partnership",
 "country_code": "MG",
 "country_name": "Madagascar",
 "types": [
  "Other"
 ]
},{
 "name": "Office National pour l'Environnement",
 "country_code": "MG",
 "country_name": "Madagascar",
 "types": [
  "Government"
 ]
},{
 "name": "Universit\u00e9 de Fianarantsoa",
 "country_code": "MG",
 "country_name": "Madagascar",
 "types": [
  "Education"
 ]
},{
 "name": "National Application Center for Pharmaceutical Research",
 "country_code": "MG",
 "country_name": "Madagascar",
 "types": [
  "Facility"
 ]
},{
 "name": "Institute Malgache De Recherches Appliqu\u00e9es",
 "country_code": "MG",
 "country_name": "Madagascar",
 "types": [
  "Nonprofit"
 ]
},{
 "name": "Madagasikara Voakajy",
 "country_code": "MG",
 "country_name": "Madagascar",
 "types": [
  "Nonprofit"
 ]
},{
 "name": "Centre National de Recherches sur l'Environnement",
 "country_code": "MG",
 "country_name": "Madagascar",
 "types": [
  "Government"
 ]
},{
 "name": "Institut National de la Statistique",
 "country_code": "MG",
 "country_name": "Madagascar",
 "types": [
  "Facility"
 ]
},{
 "name": "Ministry of Public Health",
 "country_code": "MG",
 "country_name": "Madagascar",
 "types": [
  "Government"
 ]
},{
 "name": "Minist\u00e8re de l\u2019Enseignement Sup\u00e9rieur et de la Recherche Scientifique",
 "country_code": "MG",
 "country_name": "Madagascar",
 "types": [
  "Government"
 ]
},{
 "name": "\u00c9cole Sup\u00e9rieure Polytechnique d'Antsiranana",
 "country_code": "MG",
 "country_name": "Madagascar",
 "types": [
  "Education"
 ]
}]