[{
 "name": "Aga Khan University",
 "country": "Pakistan",
 "types": [
  "Education"
 ]
},{
 "name": "University of the Punjab",
 "country": "Pakistan",
 "types": [
  "Education"
 ]
},{
 "name": "University of Karachi",
 "country": "Pakistan",
 "types": [
  "Education"
 ]
},{
 "name": "University of Peshawar",
 "country": "Pakistan",
 "types": [
  "Education"
 ]
},{
 "name": "Kohat University of Science and Technology",
 "country": "Pakistan",
 "types": [
  "Education"
 ]
},{
 "name": "Aga Khan University Hospital",
 "country": "Pakistan",
 "types": [
  "Healthcare"
 ]
},{
 "name": "Foundation University Medical College",
 "country": "Pakistan",
 "types": [
  "Education"
 ]
},{
 "name": "Liaquat University of Medical & Health Sciences",
 "country": "Pakistan",
 "types": [
  "Education"
 ]
},{
 "name": "Bahauddin Zakariya University",
 "country": "Pakistan",
 "types": [
  "Education"
 ]
},{
 "name": "Baqai Medical University",
 "country": "Pakistan",
 "types": [
  "Education"
 ]
},{
 "name": "Government College University, Lahore",
 "country": "Pakistan",
 "types": [
  "Education"
 ]
},{
 "name": "International Islamic University, Islamabad",
 "country": "Pakistan",
 "types": [
  "Education"
 ]
},{
 "name": "Gomal University",
 "country": "Pakistan",
 "types": [
  "Education"
 ]
},{
 "name": "Isra University",
 "country": "Pakistan",
 "types": [
  "Education"
 ]
},{
 "name": "Government College University, Faisalabad",
 "country": "Pakistan",
 "types": [
  "Education"
 ]
},{
 "name": "Jinnah University for Women",
 "country": "Pakistan",
 "types": [
  "Education"
 ]
},{
 "name": "Hamdard University",
 "country": "Pakistan",
 "types": [
  "Education"
 ]
},{
 "name": "Dow University of Health Sciences",
 "country": "Pakistan",
 "types": [
  "Education"
 ]
},{
 "name": "National University of Sciences and Technology",
 "country": "Pakistan",
 "types": [
  "Education"
 ]
},{
 "name": "King Edward Medical University",
 "country": "Pakistan",
 "types": [
  "Education"
 ]
},{
 "name": "University of Agriculture",
 "country": "Pakistan",
 "types": [
  "Education"
 ]
},{
 "name": "Islamia University of Bahawalpur",
 "country": "Pakistan",
 "types": [
  "Education"
 ]
},{
 "name": "Quaid-i-Azam University",
 "country": "Pakistan",
 "types": [
  "Education"
 ]
},{
 "name": "University of Sargodha",
 "country": "Pakistan",
 "types": [
  "Education"
 ]
},{
 "name": "University of Sindh",
 "country": "Pakistan",
 "types": [
  "Education"
 ]
},{
 "name": "University of Health Sciences Lahore",
 "country": "Pakistan",
 "types": [
  "Education"
 ]
},{
 "name": "University of Veterinary and Animal Sciences",
 "country": "Pakistan",
 "types": [
  "Education"
 ]
},{
 "name": "University of Agriculture Faisalabad",
 "country": "Pakistan",
 "types": [
  "Education"
 ]
},{
 "name": "University of Azad Jammu and Kashmir",
 "country": "Pakistan",
 "types": [
  "Education"
 ]
},{
 "name": "University of Balochistan",
 "country": "Pakistan",
 "types": [
  "Education"
 ]
},{
 "name": "Ziauddin University",
 "country": "Pakistan",
 "types": [
  "Education"
 ]
},{
 "name": "Abbasi Shaheed Hospital",
 "country": "Pakistan",
 "types": [
  "Healthcare"
 ]
},{
 "name": "Allama Iqbal Medical College",
 "country": "Pakistan",
 "types": [
  "Education"
 ]
},{
 "name": "Hayatabad Medical Complex",
 "country": "Pakistan",
 "types": [
  "Healthcare"
 ]
},{
 "name": "Chandka Medical College",
 "country": "Pakistan",
 "types": [
  "Education"
 ]
},{
 "name": "Army Medical College",
 "country": "Pakistan",
 "types": [
  "Education"
 ]
},{
 "name": "Health Services Academy",
 "country": "Pakistan",
 "types": [
  "Healthcare"
 ]
},{
 "name": "Ayub Medical College",
 "country": "Pakistan",
 "types": [
  "Education"
 ]
},{
 "name": "Holy Family Hospital",
 "country": "Pakistan",
 "types": [
  "Healthcare"
 ]
},{
 "name": "Bolan Medical College",
 "country": "Pakistan",
 "types": [
  "Healthcare"
 ]
},{
 "name": "Civil Hospital Karachi",
 "country": "Pakistan",
 "types": [
  "Healthcare"
 ]
},{
 "name": "Combined Military Hospital",
 "country": "Pakistan",
 "types": [
  "Healthcare"
 ]
},{
 "name": "Jinnah Medical & Dental College",
 "country": "Pakistan",
 "types": [
  "Healthcare"
 ]
},{
 "name": "Jinnah Postgraduate Medical Center",
 "country": "Pakistan",
 "types": [
  "Healthcare"
 ]
},{
 "name": "Mayo Hospital",
 "country": "Pakistan",
 "types": [
  "Healthcare"
 ]
},{
 "name": "Fatima Jinnah Medical University",
 "country": "Pakistan",
 "types": [
  "Education"
 ]
},{
 "name": "Riphah International University",
 "country": "Pakistan",
 "types": [
  "Education"
 ]
},{
 "name": "Karachi Medical and Dental College",
 "country": "Pakistan",
 "types": [
  "Education"
 ]
},{
 "name": "Frontier Medical College",
 "country": "Pakistan",
 "types": [
  "Healthcare"
 ]
},{
 "name": "Post Graduate Medical Institute",
 "country": "Pakistan",
 "types": [
  "Healthcare"
 ]
},{
 "name": "Khyber Medical College",
 "country": "Pakistan",
 "types": [
  "Healthcare"
 ]
},{
 "name": "Khyber Teaching Hospital",
 "country": "Pakistan",
 "types": [
  "Healthcare"
 ]
},{
 "name": "Punjab Medical College",
 "country": "Pakistan",
 "types": [
  "Education"
 ]
},{
 "name": "Services Institute of Medical Sciences",
 "country": "Pakistan",
 "types": [
  "Education"
 ]
},{
 "name": "Military Hospital",
 "country": "Pakistan",
 "types": [
  "Healthcare"
 ]
},{
 "name": "Shaikh Zayed Hospital",
 "country": "Pakistan",
 "types": [
  "Healthcare"
 ]
},{
 "name": "Shaikh Zayed Postgraduate Medical Institute",
 "country": "Pakistan",
 "types": [
  "Healthcare"
 ]
},{
 "name": "Shaukat Khanum Memorial Cancer Hospital and Research Center",
 "country": "Pakistan",
 "types": [
  "Healthcare"
 ]
},{
 "name": "Shifa International Hospital",
 "country": "Pakistan",
 "types": [
  "Healthcare"
 ]
},{
 "name": "Rawalpindi Medical University",
 "country": "Pakistan",
 "types": [
  "Healthcare"
 ]
},{
 "name": "Lady Reading Hospital",
 "country": "Pakistan",
 "types": [
  "Healthcare"
 ]
},{
 "name": "Lahore General Hospital",
 "country": "Pakistan",
 "types": [
  "Healthcare"
 ]
},{
 "name": "Liaquat National Hospital",
 "country": "Pakistan",
 "types": [
  "Healthcare"
 ]
},{
 "name": "Jinnah Sindh Medical University",
 "country": "Pakistan",
 "types": [
  "Education"
 ]
},{
 "name": "Nishtar Medical College and Hospital",
 "country": "Pakistan",
 "types": [
  "Other"
 ]
},{
 "name": "National Institute of Child Health",
 "country": "Pakistan",
 "types": [
  "Healthcare"
 ]
},{
 "name": "National Institute of Health",
 "country": "Pakistan",
 "types": [
  "Healthcare"
 ]
},{
 "name": "Women Medical College",
 "country": "Pakistan",
 "types": [
  "Education"
 ]
},{
 "name": "Pakistan Institute of Medical Sciences",
 "country": "Pakistan",
 "types": [
  "Healthcare"
 ]
},{
 "name": "Pakistan Health Research Council",
 "country": "Pakistan",
 "types": [
  "Government"
 ]
},{
 "name": "Fatima Jinnah Dental College",
 "country": "Pakistan",
 "types": [
  "Education"
 ]
},{
 "name": "Armed Forces Institute of Pathology",
 "country": "Pakistan",
 "types": [
  "Facility"
 ]
},{
 "name": "Punjab Institute of Cardiology",
 "country": "Pakistan",
 "types": [
  "Healthcare"
 ]
},{
 "name": "Institute of Molecular Sciences and Bioinformatics",
 "country": "Pakistan",
 "types": [
  "Education"
 ]
},{
 "name": "COMSATS University Islamabad",
 "country": "Pakistan",
 "types": [
  "Education"
 ]
},{
 "name": "Shifa Tameer-e-Millat University",
 "country": "Pakistan",
 "types": [
  "Education"
 ]
},{
 "name": "Pakistan Agricultural Research Council",
 "country": "Pakistan",
 "types": [
  "Government"
 ]
},{
 "name": "Sindh Institute of Urology and Transplantation",
 "country": "Pakistan",
 "types": [
  "Healthcare"
 ]
},{
 "name": "National Institute for Biotechnology and Genetic Engineering",
 "country": "Pakistan",
 "types": [
  "Education"
 ]
},{
 "name": "National Institute of Cardiovascular Diseases",
 "country": "Pakistan",
 "types": [
  "Healthcare"
 ]
},{
 "name": "Karachi Institute of Radiotherapy and Nuclear Medicine",
 "country": "Pakistan",
 "types": [
  "Healthcare"
 ]
},{
 "name": "Tabba Heart Institute",
 "country": "Pakistan",
 "types": [
  "Healthcare"
 ]
},{
 "name": "Nuclear Threat Initiative",
 "country": "Pakistan",
 "types": [
  "Nonprofit"
 ]
},{
 "name": "Kidney Centre",
 "country": "Pakistan",
 "types": [
  "Healthcare"
 ]
},{
 "name": "Pakistan Institute of Engineering and Applied Sciences",
 "country": "Pakistan",
 "types": [
  "Education"
 ]
},{
 "name": "Pakistan Institute of Nuclear Science and Technology",
 "country": "Pakistan",
 "types": [
  "Facility"
 ]
},{
 "name": "Pakistan Council of Scientific & Industrial Research",
 "country": "Pakistan",
 "types": [
  "Government"
 ]
},{
 "name": "Aware Girls",
 "country": "Pakistan",
 "types": [
  "Nonprofit"
 ]
},{
 "name": "Crescent Development Foundation",
 "country": "Pakistan",
 "types": [
  "Nonprofit"
 ]
},{
 "name": "National Institute Of Blood Disease and Bone Marrow Transplantation",
 "country": "Pakistan",
 "types": [
  "Healthcare"
 ]
},{
 "name": "National Institute of Population Studies",
 "country": "Pakistan",
 "types": [
  "Facility"
 ]
},{
 "name": "Uks",
 "country": "Pakistan",
 "types": [
  "Facility"
 ]
},{
 "name": "Muscular Dystrophy Patients Welfare Association",
 "country": "Pakistan",
 "types": [
  "Healthcare"
 ]
},{
 "name": "Abdul Wali Khan University Mardan",
 "country": "Pakistan",
 "types": [
  "Education"
 ]
},{
 "name": "Balochistan University of Information Technology, Engineering and Management Sciences",
 "country": "Pakistan",
 "types": [
  "Education"
 ]
},{
 "name": "Federal Urdu University",
 "country": "Pakistan",
 "types": [
  "Education"
 ]
},{
 "name": "Hazara University",
 "country": "Pakistan",
 "types": [
  "Education"
 ]
},{
 "name": "Karakoram International University",
 "country": "Pakistan",
 "types": [
  "Education"
 ]
},{
 "name": "Lahore University of Management Sciences",
 "country": "Pakistan",
 "types": [
  "Education"
 ]
},{
 "name": "NED University of Engineering and Technology",
 "country": "Pakistan",
 "types": [
  "Education"
 ]
},{
 "name": "Pir Mehr Ali Shah Arid Agriculture University",
 "country": "Pakistan",
 "types": [
  "Education"
 ]
},{
 "name": "University of Education",
 "country": "Pakistan",
 "types": [
  "Education"
 ]
},{
 "name": "University of Gujrat",
 "country": "Pakistan",
 "types": [
  "Education"
 ]
},{
 "name": "University of Lahore",
 "country": "Pakistan",
 "types": [
  "Education"
 ]
},{
 "name": "University of Malakand",
 "country": "Pakistan",
 "types": [
  "Education"
 ]
},{
 "name": "University of Science and Technology Bannu",
 "country": "Pakistan",
 "types": [
  "Education"
 ]
},{
 "name": "Sukkur IBA University",
 "country": "Pakistan",
 "types": [
  "Education"
 ]
},{
 "name": "Sindh Agriculture University",
 "country": "Pakistan",
 "types": [
  "Education"
 ]
},{
 "name": "University of Engineering and Technology Taxila",
 "country": "Pakistan",
 "types": [
  "Education"
 ]
},{
 "name": "Ghulam Ishaq Khan Institute of Engineering Sciences and Technology",
 "country": "Pakistan",
 "types": [
  "Education"
 ]
},{
 "name": "Lasbela University of Agriculture Water and Marine Science",
 "country": "Pakistan",
 "types": [
  "Education"
 ]
},{
 "name": "University of Wah",
 "country": "Pakistan",
 "types": [
  "Education"
 ]
},{
 "name": "National Textile University",
 "country": "Pakistan",
 "types": [
  "Education"
 ]
},{
 "name": "University of Faisalabad",
 "country": "Pakistan",
 "types": [
  "Education"
 ]
},{
 "name": "GIFT University",
 "country": "Pakistan",
 "types": [
  "Education"
 ]
},{
 "name": "Khyber Medical University",
 "country": "Pakistan",
 "types": [
  "Education"
 ]
},{
 "name": "University of East",
 "country": "Pakistan",
 "types": [
  "Education"
 ]
},{
 "name": "Air University",
 "country": "Pakistan",
 "types": [
  "Education"
 ]
},{
 "name": "Al-Khair University",
 "country": "Pakistan",
 "types": [
  "Education"
 ]
},{
 "name": "Bahria University",
 "country": "Pakistan",
 "types": [
  "Education"
 ]
},{
 "name": "Foundation University Islamabad",
 "country": "Pakistan",
 "types": [
  "Education"
 ]
},{
 "name": "Institute of Space Technology",
 "country": "Pakistan",
 "types": [
  "Education"
 ]
},{
 "name": "Mohammad Ali Jinnah University",
 "country": "Pakistan",
 "types": [
  "Education"
 ]
},{
 "name": "National University of Computer and Emerging Sciences",
 "country": "Pakistan",
 "types": [
  "Education"
 ]
},{
 "name": "National University of Modern Languages",
 "country": "Pakistan",
 "types": [
  "Education"
 ]
},{
 "name": "Pakistan Institute of Development Economics",
 "country": "Pakistan",
 "types": [
  "Education"
 ]
},{
 "name": "Mehran University of Engineering and Technology",
 "country": "Pakistan",
 "types": [
  "Education"
 ]
},{
 "name": "Dadabhoy Institute of Higher Education",
 "country": "Pakistan",
 "types": [
  "Education"
 ]
},{
 "name": "Greenwich University",
 "country": "Pakistan",
 "types": [
  "Education"
 ]
},{
 "name": "Indus University",
 "country": "Pakistan",
 "types": [
  "Education"
 ]
},{
 "name": "Indus Valley School of Art and Architecture",
 "country": "Pakistan",
 "types": [
  "Education"
 ]
},{
 "name": "Institute of Business Administration Karachi",
 "country": "Pakistan",
 "types": [
  "Education"
 ]
},{
 "name": "Institute of Business and Technology",
 "country": "Pakistan",
 "types": [
  "Education"
 ]
},{
 "name": "Institute of Business Management",
 "country": "Pakistan",
 "types": [
  "Education"
 ]
},{
 "name": "Iqra University",
 "country": "Pakistan",
 "types": [
  "Education"
 ]
},{
 "name": "Karachi Institute of Economics and Technology",
 "country": "Pakistan",
 "types": [
  "Education"
 ]
},{
 "name": "Khadim Ali Shah Bukhari Institute of Technology",
 "country": "Pakistan",
 "types": [
  "Education"
 ]
},{
 "name": "Newports Institute of Communications and Economics",
 "country": "Pakistan",
 "types": [
  "Education"
 ]
},{
 "name": "Preston Institute of Management Science and Technology",
 "country": "Pakistan",
 "types": [
  "Education"
 ]
},{
 "name": "Shaheed Zulfiqar Ali Bhutto Institute of Science and Technology",
 "country": "Pakistan",
 "types": [
  "Education"
 ]
},{
 "name": "Sir Syed University of Engineering and Technology",
 "country": "Pakistan",
 "types": [
  "Education"
 ]
},{
 "name": "Textile Institute of Pakistan",
 "country": "Pakistan",
 "types": [
  "Education"
 ]
},{
 "name": "Shah Abdul Latif University",
 "country": "Pakistan",
 "types": [
  "Education"
 ]
},{
 "name": "Balochistan University of Engineering and Technology",
 "country": "Pakistan",
 "types": [
  "Education"
 ]
},{
 "name": "Preston University",
 "country": "Pakistan",
 "types": [
  "Education"
 ]
},{
 "name": "Beaconhouse National University",
 "country": "Pakistan",
 "types": [
  "Education"
 ]
},{
 "name": "Forman Christian College",
 "country": "Pakistan",
 "types": [
  "Education"
 ]
},{
 "name": "Hajvery University",
 "country": "Pakistan",
 "types": [
  "Education"
 ]
},{
 "name": "Institute of Management Sciences Lahore",
 "country": "Pakistan",
 "types": [
  "Education"
 ]
},{
 "name": "Kinnaird College for Women University",
 "country": "Pakistan",
 "types": [
  "Education"
 ]
},{
 "name": "Lahore College for Women University",
 "country": "Pakistan",
 "types": [
  "Education"
 ]
},{
 "name": "Imperial College of Business Studies",
 "country": "Pakistan",
 "types": [
  "Education"
 ]
},{
 "name": "Lahore School of Economics",
 "country": "Pakistan",
 "types": [
  "Education"
 ]
},{
 "name": "Minhaj University Lahore",
 "country": "Pakistan",
 "types": [
  "Education"
 ]
},{
 "name": "National College of Arts",
 "country": "Pakistan",
 "types": [
  "Education"
 ]
},{
 "name": "National College of Business Administration and Economics",
 "country": "Pakistan",
 "types": [
  "Education"
 ]
},{
 "name": "Superior University",
 "country": "Pakistan",
 "types": [
  "Education"
 ]
},{
 "name": "University of Central Punjab",
 "country": "Pakistan",
 "types": [
  "Education"
 ]
},{
 "name": "University of Engineering and Technology Lahore",
 "country": "Pakistan",
 "types": [
  "Education"
 ]
},{
 "name": "University of Management and Technology",
 "country": "Pakistan",
 "types": [
  "Education"
 ]
},{
 "name": "University of South Asia",
 "country": "Pakistan",
 "types": [
  "Education"
 ]
},{
 "name": "Virtual University of Pakistan",
 "country": "Pakistan",
 "types": [
  "Education"
 ]
},{
 "name": "Quaid-e-Awam University of Engineering, Science and Technology",
 "country": "Pakistan",
 "types": [
  "Education"
 ]
},{
 "name": "Mohi-ud-Din Islamic University",
 "country": "Pakistan",
 "types": [
  "Education"
 ]
},{
 "name": "Northern University",
 "country": "Pakistan",
 "types": [
  "Education"
 ]
},{
 "name": "Abasyn University",
 "country": "Pakistan",
 "types": [
  "Education"
 ]
},{
 "name": "CECOS University",
 "country": "Pakistan",
 "types": [
  "Education"
 ]
},{
 "name": "City University of Science and Information Technology",
 "country": "Pakistan",
 "types": [
  "Education"
 ]
},{
 "name": "Gandhara University",
 "country": "Pakistan",
 "types": [
  "Education"
 ]
},{
 "name": "Institute of Management Sciences Peshawar",
 "country": "Pakistan",
 "types": [
  "Education"
 ]
},{
 "name": "University of Engineering and Technology Peshawar",
 "country": "Pakistan",
 "types": [
  "Education"
 ]
},{
 "name": "Qurtuba University of Science and Information Technology",
 "country": "Pakistan",
 "types": [
  "Education"
 ]
},{
 "name": "Sarhad University of Science and Information Technology",
 "country": "Pakistan",
 "types": [
  "Education"
 ]
},{
 "name": "Sardar Bahadur Khan Women's University",
 "country": "Pakistan",
 "types": [
  "Education"
 ]
},{
 "name": "Fatima Jinnah Women University",
 "country": "Pakistan",
 "types": [
  "Education"
 ]
},{
 "name": "Allama Iqbal Open University",
 "country": "Pakistan",
 "types": [
  "Education"
 ]
},{
 "name": "HITEC University",
 "country": "Pakistan",
 "types": [
  "Education"
 ]
},{
 "name": "Alkauthar Islamic University",
 "country": "Pakistan",
 "types": [
  "Education"
 ]
},{
 "name": "Ghazi University",
 "country": "Pakistan",
 "types": [
  "Education"
 ]
},{
 "name": "Lahore Leads University",
 "country": "Pakistan",
 "types": [
  "Education"
 ]
},{
 "name": "Dawood University of Engineering and Technology",
 "country": "Pakistan",
 "types": [
  "Education"
 ]
},{
 "name": "DHA Suffa University",
 "country": "Pakistan",
 "types": [
  "Education"
 ]
},{
 "name": "Iqra National University",
 "country": "Pakistan",
 "types": [
  "Education"
 ]
},{
 "name": "Mirpur University of Science and Technology",
 "country": "Pakistan",
 "types": [
  "Education"
 ]
},{
 "name": "Baba Guru Nanak University",
 "country": "Pakistan",
 "types": [
  "Education"
 ]
},{
 "name": "National Defence University",
 "country": "Pakistan",
 "types": [
  "Education"
 ]
},{
 "name": "Qarshi University",
 "country": "Pakistan",
 "types": [
  "Education"
 ]
},{
 "name": "Shaheed Benazir Bhutto University",
 "country": "Pakistan",
 "types": [
  "Education"
 ]
},{
 "name": "Shaheed Benazir Bhutto Women University",
 "country": "Pakistan",
 "types": [
  "Education"
 ]
},{
 "name": "Shaheed Mohtarma Benazir Bhutto Medical University",
 "country": "Pakistan",
 "types": [
  "Education"
 ]
},{
 "name": "University of Swat",
 "country": "Pakistan",
 "types": [
  "Education"
 ]
},{
 "name": "Universal Research Group (Pakistan)",
 "country": "Pakistan",
 "types": [
  "Company"
 ]
},{
 "name": "University of Islamic Studies",
 "country": "Pakistan",
 "types": [
  "Education"
 ]
},{
 "name": "Bahawal Victoria Hospital",
 "country": "Pakistan",
 "types": [
  "Healthcare"
 ]
},{
 "name": "Higher Education Commission",
 "country": "Pakistan",
 "types": [
  "Government"
 ]
},{
 "name": "Namal College",
 "country": "Pakistan",
 "types": [
  "Education"
 ]
},{
 "name": "Bacha Khan University",
 "country": "Pakistan",
 "types": [
  "Education"
 ]
},{
 "name": "Islamia College University",
 "country": "Pakistan",
 "types": [
  "Education"
 ]
},{
 "name": "Mari Petroleum Company (Pakistan)",
 "country": "Pakistan",
 "types": [
  "Company"
 ]
},{
 "name": "Muhammad Nawaz Sharif University of Engineering & Technology",
 "country": "Pakistan",
 "types": [
  "Education"
 ]
},{
 "name": "Rashid Latif Medical College",
 "country": "Pakistan",
 "types": [
  "Education"
 ]
},{
 "name": "Khawaja Farid Social Security Hospital",
 "country": "Pakistan",
 "types": [
  "Healthcare"
 ]
},{
 "name": "Saidu Teaching Hospital",
 "country": "Pakistan",
 "types": [
  "Healthcare"
 ]
},{
 "name": "Services Hospital",
 "country": "Pakistan",
 "types": [
  "Healthcare"
 ]
},{
 "name": "Shaikh Zayed Medical College and Hospital",
 "country": "Pakistan",
 "types": [
  "Healthcare"
 ]
},{
 "name": "Shalamar Hospital",
 "country": "Pakistan",
 "types": [
  "Healthcare"
 ]
},{
 "name": "Sindh Madressatul Islam University",
 "country": "Pakistan",
 "types": [
  "Education"
 ]
},{
 "name": "Sir Ganga Ram Hospital",
 "country": "Pakistan",
 "types": [
  "Healthcare"
 ]
},{
 "name": "St. Elizabeth's Hospital",
 "country": "Pakistan",
 "types": [
  "Healthcare"
 ]
},{
 "name": "St. Raphael's Hospital",
 "country": "Pakistan",
 "types": [
  "Healthcare"
 ]
},{
 "name": "Surgimed Hospital",
 "country": "Pakistan",
 "types": [
  "Healthcare"
 ]
},{
 "name": "University College Lahore",
 "country": "Pakistan",
 "types": [
  "Education"
 ]
},{
 "name": "University College of Islamabad",
 "country": "Pakistan",
 "types": [
  "Education"
 ]
},{
 "name": "Aga Khan Hospital for Women",
 "country": "Pakistan",
 "types": [
  "Healthcare"
 ]
},{
 "name": "Allied Hospital",
 "country": "Pakistan",
 "types": [
  "Healthcare"
 ]
},{
 "name": "Daud Memorial Hospital",
 "country": "Pakistan",
 "types": [
  "Healthcare"
 ]
},{
 "name": "Divisional Headquarters Teaching Hospital Mirpur",
 "country": "Pakistan",
 "types": [
  "Healthcare"
 ]
},{
 "name": "District Headquarters Hospital Battagram",
 "country": "Pakistan",
 "types": [
  "Healthcare"
 ]
},{
 "name": "Farooq Hospital",
 "country": "Pakistan",
 "types": [
  "Healthcare"
 ]
},{
 "name": "Center for Applied and Molecular Biology",
 "country": "Pakistan",
 "types": [
  "Education"
 ]
},{
 "name": "Ayub Agriculture Research Institute",
 "country": "Pakistan",
 "types": [
  "Government"
 ]
},{
 "name": "College of Physicians and Surgeons Pakistan",
 "country": "Pakistan",
 "types": [
  "Education"
 ]
},{
 "name": "Indus Hospital",
 "country": "Pakistan",
 "types": [
  "Healthcare"
 ]
},{
 "name": "Gmarketing (Pakistan)",
 "country": "Pakistan",
 "types": [
  "Company"
 ]
},{
 "name": "Government of Khyber Pakhtunkhwa",
 "country": "Pakistan",
 "types": [
  "Government"
 ]
},{
 "name": "Board of Intermediate Education Karachi",
 "country": "Pakistan",
 "types": [
  "Government"
 ]
},{
 "name": "Abdus Salam Centre for Physics",
 "country": "Pakistan",
 "types": [
  "Facility"
 ]
},{
 "name": "National Centre of Excellence in Analytical Chemistry",
 "country": "Pakistan",
 "types": [
  "Facility"
 ]
},{
 "name": "Pakistan Army",
 "country": "Pakistan",
 "types": [
  "Government"
 ]
},{
 "name": "Pakistan Space and Upper Atmosphere Research Commission",
 "country": "Pakistan",
 "types": [
  "Government"
 ]
},{
 "name": "Pakistan Telecommunication Company (Pakistan)",
 "country": "Pakistan",
 "types": [
  "Company"
 ]
},{
 "name": "University of Haripur",
 "country": "Pakistan",
 "types": [
  "Education"
 ]
},{
 "name": "Urban Unit",
 "country": "Pakistan",
 "types": [
  "Government"
 ]
},{
 "name": "Water and Power Development Authority",
 "country": "Pakistan",
 "types": [
  "Government"
 ]
},{
 "name": "American Institute of Pakistan Studies",
 "country": "Pakistan",
 "types": [
  "Other"
 ]
},{
 "name": "Government College of Science",
 "country": "Pakistan",
 "types": [
  "Education"
 ]
},{
 "name": "Karachi School for Business and Leadership",
 "country": "Pakistan",
 "types": [
  "Education"
 ]
},{
 "name": "SKANS School of Accountancy",
 "country": "Pakistan",
 "types": [
  "Education"
 ]
},{
 "name": "Nuclear Institute for Agriculture and Biology",
 "country": "Pakistan",
 "types": [
  "Facility"
 ]
},{
 "name": "International Center for Chemical and Biological Sciences",
 "country": "Pakistan",
 "types": [
  "Facility"
 ]
},{
 "name": "Alhamd Islamic University",
 "country": "Pakistan",
 "types": [
  "Education"
 ]
},{
 "name": "Planwel",
 "country": "Pakistan",
 "types": [
  "Education"
 ]
},{
 "name": "Government Sadiq College Women University",
 "country": "Pakistan",
 "types": [
  "Education"
 ]
},{
 "name": "Pakistan Nuclear Regulatory Authority",
 "country": "Pakistan",
 "types": [
  "Government"
 ]
},{
 "name": "Pakistan Academy of Sciences",
 "country": "Pakistan",
 "types": [
  "Government"
 ]
},{
 "name": "Aman Foundation",
 "country": "Pakistan",
 "types": [
  "Nonprofit"
 ]
},{
 "name": "World Health Organization - Pakistan",
 "country": "Pakistan",
 "types": [
  "Government"
 ]
},{
 "name": "Trust for Vaccines & Immunization",
 "country": "Pakistan",
 "types": [
  "Nonprofit"
 ]
},{
 "name": "Ziauddin Hospital",
 "country": "Pakistan",
 "types": [
  "Healthcare"
 ]
},{
 "name": "Fertility Care Multan",
 "country": "Pakistan",
 "types": [
  "Healthcare"
 ]
},{
 "name": "Pakistan Institute of Learning and Living",
 "country": "Pakistan",
 "types": [
  "Other"
 ]
},{
 "name": "Vital Pakistan Trust",
 "country": "Pakistan",
 "types": [
  "Nonprofit"
 ]
},{
 "name": "CMH Lahore Medical College and Institute of Dentistry",
 "country": "Pakistan",
 "types": [
  "Healthcare"
 ]
},{
 "name": "Ministerial Standing Committee on Scientific and Technological Cooperation of the Organization of Islamic Cooperation",
 "country": "Pakistan",
 "types": [
  "Other"
 ]
},{
 "name": "Pakistan Science Foundation",
 "country": "Pakistan",
 "types": [
  "Government"
 ]
},{
 "name": "Foundation for Research and Socio Ecological Harmony",
 "country": "Pakistan",
 "types": [
  "Nonprofit"
 ]
},{
 "name": "Sustainable Development Policy Institute",
 "country": "Pakistan",
 "types": [
  "Nonprofit"
 ]
},{
 "name": "Pakistan Atomic Energy Commission",
 "country": "Pakistan",
 "types": [
  "Government"
 ]
},{
 "name": "Government of Pakistan",
 "country": "Pakistan",
 "types": [
  "Government"
 ]
},{
 "name": "Remedial Centre Hospital",
 "country": "Pakistan",
 "types": [
  "Healthcare"
 ]
},{
 "name": "Baqai Institute of Diabetology and Endocrinology",
 "country": "Pakistan",
 "types": [
  "Healthcare"
 ]
},{
 "name": "Karachi Institute of Heart Diseases",
 "country": "Pakistan",
 "types": [
  "Healthcare"
 ]
},{
 "name": "Rahnuma",
 "country": "Pakistan",
 "types": [
  "Other"
 ]
},{
 "name": "Pakistan Association of Cognitive Therapists",
 "country": "Pakistan",
 "types": [
  "Nonprofit"
 ]
},{
 "name": "Marie Stopes Society",
 "country": "Pakistan",
 "types": [
  "Other"
 ]
},{
 "name": "Benazir Bhutto Hospital",
 "country": "Pakistan",
 "types": [
  "Healthcare"
 ]
},{
 "name": "Ministry of National Health Services Regulation and Coordination",
 "country": "Pakistan",
 "types": [
  "Government"
 ]
},{
 "name": "Human Development Research Foundation",
 "country": "Pakistan",
 "types": [
  "Nonprofit"
 ]
},{
 "name": "Omair Sana Foundation",
 "country": "Pakistan",
 "types": [
  "Nonprofit"
 ]
},{
 "name": "Aga Khan Development Network",
 "country": "Pakistan",
 "types": [
  "Other"
 ]
},{
 "name": "Democratic Commission for Human Development",
 "country": "Pakistan",
 "types": [
  "Nonprofit"
 ]
},{
 "name": "Pakistan Environmental Protection Agency",
 "country": "Pakistan",
 "types": [
  "Government"
 ]
},{
 "name": "Pakistan Council of Research in Water Resources",
 "country": "Pakistan",
 "types": [
  "Government"
 ]
},{
 "name": "Abbottabad University of Science and Technology",
 "country": "Pakistan",
 "types": [
  "Education"
 ]
},{
 "name": "Bilquis Postgraduate College For Women",
 "country": "Pakistan",
 "types": [
  "Education"
 ]
},{
 "name": "Center for Non-Communicable Diseases",
 "country": "Pakistan",
 "types": [
  "Facility"
 ]
},{
 "name": "Information Technology University",
 "country": "Pakistan",
 "types": [
  "Education"
 ]
},{
 "name": "Habib University",
 "country": "Pakistan",
 "types": [
  "Education"
 ]
},{
 "name": "National Engineering and Scientific Commission",
 "country": "Pakistan",
 "types": [
  "Government"
 ]
},{
 "name": "Kharadar General Hospital",
 "country": "Pakistan",
 "types": [
  "Healthcare"
 ]
},{
 "name": "Northwest General Hospital and Research Center",
 "country": "Pakistan",
 "types": [
  "Healthcare"
 ]
},{
 "name": "Rural Development Foundation of Pakistan",
 "country": "Pakistan",
 "types": [
  "Nonprofit"
 ]
},{
 "name": "Shirkat Gah",
 "country": "Pakistan",
 "types": [
  "Nonprofit"
 ]
},{
 "name": "Sobhraj Maternity Hospital",
 "country": "Pakistan",
 "types": [
  "Healthcare"
 ]
},{
 "name": "Aitchison College",
 "country": "Pakistan",
 "types": [
  "Education"
 ]
},{
 "name": "Fauji Fertilizer (Pakistan)",
 "country": "Pakistan",
 "types": [
  "Company"
 ]
},{
 "name": "Ministry of Industries and Production",
 "country": "Pakistan",
 "types": [
  "Government"
 ]
},{
 "name": "United States Educational Foundation in Pakistan",
 "country": "Pakistan",
 "types": [
  "Education"
 ]
},{
 "name": "University of Swabi",
 "country": "Pakistan",
 "types": [
  "Education"
 ]
},{
 "name": "Indus Resource Centre",
 "country": "Pakistan",
 "types": [
  "Nonprofit"
 ]
},{
 "name": "The TAU Institute",
 "country": "Pakistan",
 "types": [
  "Other"
 ]
},{
 "name": "FATA University",
 "country": "Pakistan",
 "types": [
  "Education"
 ]
},{
 "name": "Government College Women University Faisalabad",
 "country": "Pakistan",
 "types": [
  "Education"
 ]
},{
 "name": "Institute of Business Leadership",
 "country": "Pakistan",
 "types": [
  "Education"
 ]
},{
 "name": "Central Cotton Research Institute",
 "country": "Pakistan",
 "types": [
  "Government"
 ]
},{
 "name": "National University of Medical Sciences",
 "country": "Pakistan",
 "types": [
  "Education"
 ]
},{
 "name": "Nur International University",
 "country": "Pakistan",
 "types": [
  "Education"
 ]
},{
 "name": "University of Okara",
 "country": "Pakistan",
 "types": [
  "Education"
 ]
},{
 "name": "Pakistan Scientific and Technological Information Centre",
 "country": "Pakistan",
 "types": [
  "Government"
 ]
},{
 "name": "Capital University of Science and Technology",
 "country": "Pakistan",
 "types": [
  "Education"
 ]
},{
 "name": "Bridge Consultants Foundation",
 "country": "Pakistan",
 "types": [
  "Nonprofit"
 ]
},{
 "name": "The Women University Multan",
 "country": "Pakistan",
 "types": [
  "Education"
 ]
},{
 "name": "Indrashil University",
 "country": "Pakistan",
 "types": [
  "Education"
 ]
},{
 "name": "Khwaja Fareed University of Engineering and Information Technology",
 "country": "Pakistan",
 "types": [
  "Education"
 ]
},{
 "name": "Innovative Scientific Information & Services Network",
 "country": "Pakistan",
 "types": [
  "Nonprofit"
 ]
}]